autocombobox/__init__.py
autocombobox/autocombobox.py
autocombobox/filters.py
autocombobox-1.5.0.dist-info/METADATA
autocombobox-1.5.0.dist-info/WHEEL
autocombobox-1.5.0.dist-info/licenses/LICENSE
autocombobox-1.5.0.dist-info/RECORD
