Metadata-Version: 2.3
Name: autocombobox
Version: 1.5.0
Summary: Insert a Combobox into your GUI that allows suggestions based on what the user writes in
Project-URL: Homepage, https://github.com/Church-17/autocombobox
Author-email: Matteo Chiesa <matteo.chiesa.mc@gmail.com>
Maintainer-email: Matteo Chiesa <matteo.chiesa.mc@gmail.com>
License:                     GNU GENERAL PUBLIC LICENSE
Keywords: autocomplete,autocompleting,combobox,suggestion,tk,tkinter,ttk
Classifier: Development Status :: 4 - Beta
Classifier: Intended Audience :: Developers
Classifier: License :: OSI Approved :: GNU General Public License v3 (GPLv3)
Classifier: Programming Language :: Python
Classifier: Programming Language :: Python :: 3
Requires-Python: >=3.10
